pymatch/Matcher.py
pymatch/__init__.py
pymatch/functions.py
pymatch-0.2.8.dist-info/DESCRIPTION.rst
pymatch-0.2.8.dist-info/METADATA
pymatch-0.2.8.dist-info/RECORD
pymatch-0.2.8.dist-info/WHEEL
pymatch-0.2.8.dist-info/metadata.json
pymatch-0.2.8.dist-info/top_level.txt
