Metadata-Version: 2.0
Name: pymatch
Version: 0.2.8
Summary: Matching techniques for Observational Studies
Home-page: https://github.com/benmiroglio/pymatch
Author: Ben Miroglio
Author-email: benmiroglio@gmail.com
License: UNKNOWN
Download-URL: https://github.com/benmiroglio/pymatch/archive/0.2.8.tar.gz
Keywords: logistic,regression,matching,observational,study,causal,inference
Platform: UNKNOWN
Requires: seaborn
Requires: statsmodels
Requires: scipy
Requires: patsy
Requires: matplotlib
Requires: pandas
Requires: numpy
